{"requestId":"677ba23470981449447b26a771b28a8a","resolvedSearchType":"neural","results":[{"id":"https://www.unleash.ai/hr-technology/the-five-2026-hr-tech-acquisitions-that-put-hr-buyers-in-a-strong-position/","title":"The five 2026 HR tech acquisitions that put HR buyers in a strong ...","url":"https://www.unleash.ai/hr-technology/the-five-2026-hr-tech-acquisitions-that-put-hr-buyers-in-a-strong-position/","publishedDate":"2026-03-03T00:00:00.000Z","text":"The five 2026 HR tech acquisitions that put HR buyers in a strong position | UNLEASH \n\n \n\n \n\nShare\n\nAnalysis| HR Technology\n\n# The five 2026 HR tech acquisitions that put HR buyers in a strong position\n\nThe first two months of 2026 have seen five acquisitions in the HR tech space. UNLEASH spoke with industry analyst Josh Bersin, as well as executives from the five acquiring companies, to find out what this means for the sector, and specifically HR tech buyers.\n\nMarch 03, 2026, 01:42 PM | By: Allie Nawrat\n\n##### Acquisition analysis\n\nFollowing a healthy M&A flow last year, 2026 has started with a bang in the HR tech sector.\n\nThere have been five acquisitions so far this year - what do these mean for HR tech buyers?\n\nUNLEASH investigates with the help of industry analyst Josh Bersin, and HR tech executives from the companies leading the 2026 acquisitions.\n\nShare\n\nWe’re two months into 2026 and it’s been a busy eight weeks for the HR technology sector.\n\nThere have been multiple CEO changes – notably at Workday, Oyster and Culture Amp– numerous investment rounds, but particularly significant are the mergers & acquisitions (M&A).\n\nSo far in 2026, there have been five noteworthy acquisitions; Payoneer bought Boundless, Remote purchased Atlas, Phenom’s acquisition of Be Applied and Included AI, Docebo bought 365Talents, and Percepytx’s purchase of AI native learning platform Lyceum.\n\nThese five deals build on a healthy M&A pipeline in 2025.\n\nGiven that acquisitions act as signals about where money, talent and innovation are flowing in the sector, let’s dig into what these five deals say about the HR tech space.\n\nUNLEASH spoke to executives at the five purchasing HR tech vendors , as well as Josh Bersin, industry analyst and CEO of The Josh Bersin Company, to find out what decisions HR tech buyers need to make as a result of these acquisitions.\n\n## How 2026 HR tech acquisitions affect HR buyers\n\nTalking about the five deals as a whole, Bersin tells UNLEASH that they show that “bigger players are all on the hunt for new, HR tech vendors with an AI story to acquire, for tech, customers, and skills”.\n\nUltimately, big vendors are looking to buy innovative tech, as well as to grow customer bases and better serve HR’s needs.\n\nSpeaking exclusively to UNLEASH, Phenom’s CEO and Co-Founder Mahe Bayireddi shares that when the talent intelligence platform is thinking about acquisitions, there are three requirements: alignment with the innovation pipeline, culture fit and value for customers.\n\nThe purchases of agentic people analytics platform, Included AI, and AI cognitive assessment solution, Be Applied, fit with all three – they “will have a major impact on addressing our customers’ biggest data challenges in areas such as people analytics, workforce planning and skills-based hiring”.\n\nAs Ross Wainwright, CEO at employee experience ","highlights":["The five 2026 HR tech acquisitions that put HR buyers in a strong position | UNLEASH \n\n \n\n \n\nShare Analysis| HR Technology\n\n# The five 2026 HR tech acquisitions that put HR buyers in a strong position The first two months of 2026 have seen five acquisitions in the HR tech space. UNLEASH spoke with industry analyst Josh Bersin, as well as executives from the five acquiring companies, to find out what this means for the sector, and   ...    March 03, 2026, 01:42 PM | By: Allie Nawrat\n\n##### Acquisition analysis Following a healthy M&A flow last year, 2026 has started with a bang in the HR tech sector. There have been five acquisitions so far this year - what do these mean for HR tech buyers? UNLEASH investigates with the help of industry analyst Josh Bersin, and HR tech executives from the companies leading the 2026 acquisitions. Share\n\nWe’re two months into 2026 and it’s been a busy eight weeks for the HR technology sector. There have been multiple CEO changes – notably at Workday, Oyster and Culture Amp– numerous investment rounds, but particularly significant are the mergers & acquisitions (M&A). So far in 2026, there have been five noteworthy acquisitions; Payoneer bought Boundless, Remote purchased Atlas, Phenom’s acquisition of Be Applied and Included AI, Docebo bought 365Talents, and Percepytx’s purchase of AI native learning platform Lyceum. These five deals build on a healthy M&A pipeline in 2025. Given that acquisitions act as signals about where money, talent and innovation are flowing in the sector, let’s dig into what these five deals say about the HR tech space. UNLEASH spoke to executives at the five purchasing HR tech vendors , as well as Josh Bersin, industry analyst and CEO of The Josh Bersin Company, to find out what decisions HR tech buyers need to make as a result of these acquisitions. ## How 2026 HR tech acquisitions affect HR buyers Talking about the five deals as a whole, Bersin tells UNLEASH that they show that “bigger players are all on the hunt for new, HR tech vendors with an AI story to acquire, for tech, customers, and skills”. Ultimately, big vendors are looking to buy innovative tech, as well as to grow customer bases and better serve HR’s needs. Speaking exclusively to UNLEASH, Phenom’s CEO and Co-Founder Mahe Bayireddi shares that when the talent intelligence platform is thinking about acquisitions, there are three requirements: alignment with the innovation pipeline, culture   ...    The purchases of agentic people analytics platform, Included AI, and AI cognitive assessment solution, Be Applied, fit with all three – they “will have a major"],"highlightScores":[-0.04736328125],"image":"https://www.unleash.ai/wp-content/uploads/2026/03/AdobeStock_1492138661.jpeg","favicon":"https://www.unleash.ai/wp-content/uploads/2021/10/cropped-UNLEASH_Favicon_512x512-32x32.png"},{"id":"https://prnewswire.com/news-releases/remote-acquires-atlas-to-simplify-how-global-teams-spend-and-scale-302665591.html","title":"Remote acquires Atlas to simplify how global teams spend and scale","url":"https://prnewswire.com/news-releases/remote-acquires-atlas-to-simplify-how-global-teams-spend-and-scale-302665591.html","publishedDate":"2026-01-20T00:00:00.000Z","author":"Remote","text":"Remote acquires Atlas to simplify how global teams spend and scale Accessibility Statement Skip Navigation\n\nAcquisition will bolster Remote's HR and payroll platform with integrated financial tools to streamline operations for modern workforces\n\nSAN FRANCISCO, Jan. 20, 2026 /PRNewswire/ -- Remote, the leading global employment operating system, has completed the acquisition of Atlas, the expense management solution for global teams. The acquisition provides the foundation for a new category of products from Remote to enable customers to offer more holistic and modern employee experiences to their teams.\n\nWith companies of all sizes now hiring far beyond their HQ cities, managing the day-to-day financial operations of a distributed team remains a fragmented process. Led by co-founders Karen Serfaty and Gianina Rossi, Atlas solves this by offering a unified, AI-native platform for global teams including:\n\n- The Atlas Card: The first global employee card designed specifically for remote teams, allowing companies to manage expenses and stipends for employees worldwide with customized rules and global support.\n- Flexible Points System: Allowing companies to allocate budgets without processing reimbursements, while letting employees select their own perks, such as wellness, transit, or entertainment.\n- Integrated Global Healthcare: The ability to offer and manage local health insurance across multiple key markets, including the U.S., Mexico, Colombia, and Argentina, from a single dashboard.\n\n\"The complexity of cross-border financial management is one of the last great barriers to truly efficient global operations,\" said Job van der Voort, co-founder and CEO of Remote. \"From the first time I met the Atlas team, I was impressed by the elegance and depth of the solutions they've built to this problem. By building Atlas into Remote, we can more effectively solve those daily headaches for our customers and make life better for their teams. I'm thrilled to welcome such a talented group of builders who share our obsession with making global employment feel truly local.\"\n\n\"We started Atlas because we believe that everyone, regardless of where they are located, should have access to the best working conditions. Part of solving this problem means providing global employees with access to financial solutions like a personal employee card and benefits such as healthcare,\" said Karen Serfaty, co-founder and CEO of Atlas. \"We are big fans of the work that Job, Marcelo, and the Remote team have done to advance the vision of a global workforce. We are joining Remote because we believe that we can get further together. We are very excited for the future of global employment and for all things to come for teams choosing Remote in 2026.\"\n\nTo sign up or learn more about Remote, visit remote.com. And, to learn more about Atlas as the newest tool in Remote's toolbox, visit https://www.heyatlas.com/.\n\nAbout Remote: ","highlights":["Remote acquires Atlas to simplify how global teams spend and scale Accessibility Statement Skip Navigation Acquisition will bolster Remote's HR and payroll platform with integrated financial tools to streamline operations for modern workforces SAN FRANCISCO, Jan. 20, 2026 /PRNewswire/ -- Remote, the leading global employment operating system, has completed the acquisition of Atlas, the expense management solution for global teams. The acquisition provides the foundation for a new category of products from Remote to enable customers to offer more holistic and modern employee experiences to their teams. With companies of all sizes now hiring far beyond their HQ cities, managing the day-to-day financial operations of a distributed team remains a fragmented process. Led by co-founders Karen Serfaty and Gianina Rossi, Atlas solves this by offering a unified, AI-native platform for global teams including: - The Atlas Card: The first global employee card designed specifically for remote teams, allowing companies to manage   ...    - Flexible Points System: Allowing companies to allocate budgets without processing reimbursements, while letting employees select their own perks, such as wellness, transit, or entertainment.   ...    including the U.S., Mexico, Colombia, and Argentina, from a single dashboard. \"The complexity of cross-border financial management is one of the last great barriers to truly efficient global operations,\" said Job van der Voort, co-founder and CEO of Remote. \"From the first time I met the Atlas team, I was impressed by the elegance and depth of the solutions they've built to this problem. By building Atlas into Remote, we can more effectively solve those daily headaches for our customers and make life better for their teams. I'm thrilled to welcome such a talented group of builders who share our obsession with making global employment feel truly local.\" \"We started Atlas because we believe that everyone, regardless of where they are located, should have access to the best working conditions. Part of solving this problem means providing global employees with access to financial solutions like a personal employee card and benefits such as healthcare,\" said Karen Serfaty, co-founder and CEO of Atlas. \"We are big fans of the work that Job, Marcelo, and the Remote team have done to advance the vision of a global workforce. We are joining Remote because we believe that we can get further together. We are very excited for the future of global employment and for all things to come for teams choosing Remote in 2026.\" To sign up or learn more about Remote, visit remote.com. And, to learn more about Atlas as the newest tool in Remote's toolbox, visit https://www.heyatlas.com/. About Remote:"],"highlightScores":[-0.08740234375],"image":"https://mma.prnewswire.com/media/2735658/Remote_Horizontal_Purple_Logo.jpg?p=facebook","favicon":"https://prnewswire.com/content/dam/prnewswire/icons/2019-Q4-PRN-Icon-32-32.png"},{"id":"https://tracxn.com/d/acquisitions/acquisitions-by-deel/__0QGPRxeNO6btLSLEVFaxlsxExp-2aMVx74Et0xat7KU","title":"List of 10 Acquisitions by Deel (Jan 2026) - Tracxn","url":"https://tracxn.com/d/acquisitions/acquisitions-by-deel/__0QGPRxeNO6btLSLEVFaxlsxExp-2aMVx74Et0xat7KU","publishedDate":"2026-01-01T00:00:00.000Z","text":"List of 10 Acquisitions by Deel (Jan 2026) - Tracxn\n\nYour browser was unable to load all of Tracxn resources. They may have been blocked by your firewall, proxy or browser configuration. Press Ctrl+F5 or Ctrl+Shift+R to have your browser try again and if that doesn't work, click here to retry or mail us at hi@tracxn.com\n\nInternal Server Error\n\n# Acquisitions by Deel\n\nLast updated: January 1, 2026\n\nSuggest Edits\n\nCopy Url\n\n- Email\n- Facebook\n- Twitter\n- Linkedin\n\n- Request page removal\n\n## List of Deel's Acquisitions\n\nFilter this list\n\nDeel has completed a total of 10 acquisitions. These acquisitions span 6 distinct sectors, primarily HRTech(4 acquisitions), Finance & Accounting Tech(4 acquisitions), and Digital Remittance(1 acquisition). Geographically, the activity has spanned 5 countries, concentrated in United States(4 acquisitions), United Kingdom(2 acquisitions), and Germany(2 acquisitions). Peak acquisition years include 2024 with 5 acquisitions, 2022 with 3 acquisitions, and 2023 with 1 acquisition. Over the last five years (2020-2025), the average number of acquisitions per year stands at 2. As of the current calendar year, 2024, 0 acquisitions have been completed. The most recent acquisition was Assemble, a cloud-based platform for compensation planning founded in 2020 in San Francisco, which occurred in December 2024.\n\nHere's the year on year acquisition history of Deel:\n\n2024202320222021Acquisitions Round Date (Yearly)012345\n\n- Number of Total Acquisitions\n\nYear\n\n# Acquisitions\n\n2024\n\n5\n\n2023\n\n1\n\n2022\n\n3\n\n2021\n\n1\n\nView all Acquisitions by Deel\n\n### Recent acquisitions by Deel\n\nDeel's most recent acquisition - Assemble is a Cloud-based platform for compensation planning, founded in 2020 and located in San Francisco. Deel acquired it in December 2024.\n\nHere is the list of all acquisitions by Deel sorted by the latest acquisition date:\n\nAcquired on\n\nAcquired Company\n\nAcquisition Price\n\nFacilitators\n\nStake Acquired\n\nAcquisition Multiple\n\nDec 19, 2024\n\nAssemble\n\nUndisclosed\n\n-\n\n76\n\n902\n\nNov 29, 2024\n\nAtlantic Money\n\nUndisclosed\n\n-\n\n36\n\n529\n\nJul 18, 2024\n\nHofy\n\nUndisclosed\n\n-\n\n34\n\n694\n\nMar 05, 2024\n\nPaySpace\n\nUndisclosed\n\nOrrick\n\n95\n\n762\n\nFeb 28, 2024\n\nZavvy\n\nUndisclosed\n\nOrrick\n\n46\n\n707\n\nView the full list of acquisitions\n\nSign Up for Free\n\n## News related to Deel's acquisitions\n\nFilter this list\n\nMedia has covered Deel for a total of 37 events in the last 1 year, 9 of them have been about acquisition activity.\n\n•\n\nArsenal Partners with Deel as Official HR Platform Bdaily•Dec 12, 2025• Deel, Arsenal\n\n•\n\nEleap Integrates With Deel For Automatic User Synchronization And Improved Performance Management","highlights":["List of 10 Acquisitions by Deel (Jan 2026) - Tracxn   ...    Internal Server Error\n\n# Acquisitions by Deel\n\nLast updated: January 1, 2026\n\nSuggest Edits\n\nCopy Url - Email\n- Facebook\n- Twitter\n- Linkedin\n\n- Request page removal\n\n## List of Deel's Acquisitions\n\nFilter this list Deel has completed a total of 10 acquisitions. These acquisitions span 6 distinct sectors, primarily HRTech(4 acquisitions), Finance & Accounting Tech(4 acquisitions), and Digital Remittance(1 acquisition). Geographically, the activity has spanned 5 countries, concentrated in United States(4 acquisitions), United Kingdom(2 acquisitions), and Germany(2 acquisitions). Peak acquisition years include 2024 with 5 acquisitions, 2022 with 3 acquisitions, and 2023 with 1 acquisition. Over the last five years (2020-2025), the average number of acquisitions per year stands at 2. As of the current calendar year, 2024, 0 acquisitions have been completed. The most recent acquisition was Assemble, a cloud-based platform for compensation planning founded in 2020 in San Francisco, which occurred in December 2024. Here's the year on year acquisition history of Deel:\n\n2024202320222021Acquisitions Round Date (Yearly)012345 - Number of Total Acquisitions\n\nYear\n\n# Acquisitions\n\n2024\n\n5\n\n2023\n\n1\n\n2022\n\n3\n\n2021\n\n1   ...    Deel's most recent acquisition - Assemble is a Cloud-based platform for compensation planning, founded in 2020 and located in San Francisco. Deel acquired it in December 2024. Here is the list of all acquisitions by Deel sorted by the latest acquisition date:\n\nAcquired on\n\nAcquired Company Acquisition Price\n\nFacilitators\n\nStake Acquired\n\nAcquisition Multiple\n\nDec 19, 2024\n\nAssemble\n\nUndisclosed\n\n-\n\n76\n\n902 Nov 29, 2024\n\nAtlantic Money\n\nUndisclosed\n\n-\n\n36\n\n529\n\nJul 18, 2024\n\nHofy\n\nUndisclosed\n\n-\n\n34\n\n694\n\nMar 05, 2024 PaySpace\n\nUndisclosed\n\nOrrick\n\n95\n\n762\n\nFeb 28, 2024\n\nZavvy\n\nUndisclosed\n\nOrrick\n\n46\n\n707 View the full list of acquisitions\n\nSign Up for Free\n\n## News related to Deel's acquisitions\n\nFilter this list Media has covered Deel for a total of 37 events in the last 1 year, 9 of them have been about acquisition activity.\n\n• Arsenal Partners with Deel as Official HR Platform Bdaily•Dec 12, 2025• Deel, Arsenal\n\n• Eleap Integrates With De"],"highlightScores":[0.259765625],"image":"https://cdn.tracxn.com/images/seo/social/acquisitions/acquisitions-by-deel-overview-1752812715659.webp","favicon":"https://cdn.tracxn.com/images/static/favicon.ico"},{"id":"https://www.reuters.com/business/payroll-platform-deel-valued-173-billion-latest-funding-round-2025-10-16/","title":"Deel hits $17.3 billion valuation, aims to expand globally | Reuters","url":"https://www.reuters.com/business/payroll-platform-deel-valued-173-billion-latest-funding-round-2025-10-16/","publishedDate":"2025-10-16T00:00:00.000Z","author":"Jaspreet Singh","text":"Deel hits $17.3 billion valuation, aims to expand globally | Reuters\n\nExclusive news, data and analytics for financial market professionalsLearn more aboutRefinitiv\n\nOct 16 (Reuters) - Payroll startup Deel said on Thursday it raised $300 million in a funding round, led by new investor Ribbit Capital alongside existing backers Andreessen Horowitz and Coatue Management, valuing the company at $17.3 billion.\n\nThe San Francisco, California-based company said it plans to use the fresh capital for acquisitions and expand its payroll infrastructure with a goal of offering native payroll in more than 100 countries by 2029.\n\n Sign up here.\n\nThe Series E fundraise comes amid its ongoing litigation with rival Rippling, which has sued Deel alleging racketeering, trade‑secret misappropriation and unfair competition, while Deel filed a defamation suit against Rippling in April, calling the claims a multi‑year smear campaign.\n\nEarlier this year, Rippling raised $450 million in a Series G funding round, valuing the company at $16.8 billion.\n\nDeel Chief Executive Alex Bouaziz declined to comment on the litigation but termed it as a \"frivolous lawsuit\".\n\nBouaziz said Deel crossed $100 million monthly revenue for the first time in September and it generates roughly $15 million to $17 million in earnings before interest, taxes, depreciation and amortization.\n\nFounded in 2019, Deel provides services to help companies hire international employees and contractors while ensuring compliance with local labor laws. It also automates payroll processing for businesses operating across multiple countries.\n\nDeel was earlier valued at $12.6 billion after a $300 million secondary purchase by General Catalyst and Abu Dhabi's Mubadala earlier this year.\n\nThe company recently acquired its London-based competitor Omnipresent in a deal worth around $15 million, according to a person familiar with the matter.\n\nDeel had crossed $1 billion annual revenue run rate in the first quarter and earmarked up to $500 million for acquisitions this year to bolster growth, the company previously said.\n\nReporting by Jaspreet Singh in Bengaluru; Editing by Vijay Kishore\n\nOur Standards: The Thomson Reuters Trust Principles., opens new tab\n\nPurchase Licensing Rights\n\n## Business\n\n### Bank of Canada says it will have a tough job tackling structural changes\n\nWorldcategory· March 26, 2026 · 5:12 PM UTC · ago\n\nBy Promit Mukherjee and David Ljunggren\n\nBoards, Policy & Regulationcategory Crypto platform Anchorage brings Sun's Tron to US investors\n\nFinancecategory UBS halts withdrawals from $469 million real estate fund for up to 3 years\n\nBusinesscategory Stryker says manufacturing mostly restored after cyberattack\n\nSustainabilitycategory Algeria and Spain agree to strengthen energy partnership","highlights":["Deel hits $17.3 billion valuation, aims to expand globally | Reuters   ...    Oct 16 (Reuters) - Payroll startup Deel said on Thursday it raised $300 million in a funding round, led by new investor Ribbit Capital alongside existing backers Andreessen Horowitz and Coatue Management, valuing the company at $17.3 billion. The San Francisco, California-based company said it plans to use the fresh capital for acquisitions and expand its payroll infrastructure with a goal of offering native payroll in more than 100 countries by 2029. Sign up here. The Series E fundraise comes amid its ongoing litigation with rival Rippling, which has sued Deel alleging racketeering, trade‑secret misappropriation and unfair competition, while Deel filed a defamation suit against Rippling in April, calling the claims a multi‑year smear campaign. Earlier this year, Rippling raised $450 million in a Series G funding round, valuing the company at $16.8 billion. Deel Chief Executive Alex Bouaziz declined to comment on the litigation but termed it as a \"frivolous lawsuit\". Bouaziz said Deel crossed $100 million monthly revenue for the first time in September and it generates roughly $15 million to $17 million in earnings before interest, taxes, depreciation and amortization. Founded in 2019, Deel provides services to help companies hire international employees and contractors while ensuring   ...    countries. Deel was earlier valued at $12.6 billion after a $300 million secondary purchase by General Catalyst and Abu Dhabi's Mubadala earlier this year. The company recently acquired its London-based competitor Omnipresent in a deal worth around $15 million, according to a person familiar with the matter. Deel had crossed $1 billion annual revenue run rate in the first quarter and earmarked up to $500 million for acquisitions this year to bolster growth, the company previously said.   ...    ### Bank of Canada says it will have a tough job tackling structural changes Worldcategory· March 26, 2026 · 5:12 PM UTC · ago\n\nBy Promit Mukherjee and David Ljunggren Boards, Policy & Regulationcategory Crypto platform Anchorage brings Sun's Tron to US investors Financecategory UBS halts withdrawals from $469 million real estate fund for up to"],"highlightScores":[0.1083984375],"image":"https://www.reuters.com/resizer/v2/466BJJQ7PVGY5O53NZ3KL65MHM.png?auth=b9c3bf166c40a6778eb5672993fde7c30a15f48329026674eff92afd8da1d0ca&height=1005&width=1920&quality=80&smart=true","favicon":"https://www.reuters.com/pf/resources/images/reuters/favicon/tr_fvcn_kinesis_32x32_v2.ico?d=355"},{"id":"https://pulse2.com/remote-buys-atlas/","title":"Remote Acquires Atlas To Add Expense Management And Employee Financial Tools For Global Teams","url":"https://pulse2.com/remote-buys-atlas/","publishedDate":"2026-01-20T00:00:00.000Z","author":"Amit Chowdhry","text":"Remote Acquires Atlas To Add Expense Management And Employee Financial Tools For Global Teams \n\n# Remote Acquires Atlas To Add Expense Management And Employee Financial Tools For Global Teams\n\nBy Amit Chowdhry • Jan 20, 2026\n\nRemote Acquires Atlas To Add Expense Management And Employee Financial Tools For Global Teams\n\nRemote has acquired Atlas, an expense management and corporate card platform built for distributed workforces, in a move to add integrated financial tooling to Remote’s global employment, HR, and payroll operating system. The companies said the deal will help customers simplify cross-border spend, perks, and benefits administration as hiring continues to expand far beyond headquarters locations.\n\nRemote, founded in 2019 by Job van der Voort and Marcelo Lebre, positions the acquisition as the starting point for a broader product expansion focused on delivering more “holistic and modern employee experiences” within a single platform. Atlas, led by co-founders Karen Serfaty and Gianina Rossi, brings an AI-native approach to employee spending and benefits management designed for teams operating across multiple countries and currencies.\n\nThe acquisition centers on consolidating a set of tools Atlas built to reduce the operational friction that can arise when global teams rely on separate providers for cards, stipends, reimbursements, and localized benefits. Atlas’s offering includes a global employee card tailored for remote teams, configurable spending rules, and support for managing employee expenses and stipends worldwide. It also includes a flexible points-based system that helps companies allocate budgets without running traditional reimbursement workflows, while allowing employees to choose perks across categories such as wellness and transit. In addition, Atlas supports managing local health insurance across multiple markets—including the U.S., Mexico, Colombia, and Argentina—through a single dashboard.\n\nRemote said embedding Atlas into its platform will help customers address what it described as one of the remaining barriers to smooth international operations: day-to-day financial management for distributed workforces. The combined capability is expected to appeal to companies looking to standardize how employees spend company funds and access benefits across regions, while maintaining governance and compliance controls.\n\nRemote is backed by investors including SoftBank, Accel, Sequoia, Index Ventures, Two Sigma Ventures, General Catalyst, and B Capital. Atlas has been backed by a group of investors, including Hi Ventures, Daniel Gross, Jason Calacanis, Claire Hughes Johnson, Lauran Behrens, Oskar Hjertonsson, 2048 Ventures, Ride Ventures, First Row Partners, Michael Manne, and Ben Tossel. Financial terms of the acquisition were not disclosed.\n\nKEY QUOTES:\n\n“The complexity of cross-border financial management is one of the last great barriers to truly efficient global operations. From the first time I met the Atlas team, I was ","highlights":["Remote Acquires Atlas To Add Expense Management And Employee Financial Tools For Global Teams # Remote Acquires Atlas To Add Expense Management And Employee Financial Tools For Global Teams By Amit Chowdhry • Jan 20, 2026 Remote Acquires Atlas To Add Expense Management And Employee Financial Tools For Global Teams Remote has acquired Atlas, an expense management and corporate card platform built for distributed workforces, in a move to add integrated financial tooling to Remote’s global employment, HR, and payroll operating system. The companies said the deal will help customers simplify cross-border spend, perks, and benefits administration as hiring continues to expand far beyond headquarters locations. Remote, founded in 2019 by Job van der Voort and Marcelo Lebre, positions the acquisition as the starting point for a broader product expansion focused on delivering more “holistic and modern employee experiences” within a single platform. Atlas, led by co-founders Karen Serfaty and Gianina Rossi, brings an AI-native approach to employee spending and benefits management designed for teams operating across multiple countries and currencies. The acquisition centers on consolidating a set of tools Atlas built to reduce the operational friction that can arise when global teams rely on separate providers for cards, stipends, reimbursements, and localized benefits. Atlas’s offering includes a global employee card tailored for remote teams, configurable spending rules, and support for managing employee expenses and stipends worldwide. It also includes a flexible points-based system that helps companies   ...    markets—including the U.S., Mexico, Colombia, and Argentina—through a single dashboard. Remote said embedding Atlas into its platform will help customers address what it described as one of the remaining barriers to smooth international operations: day-to-day financial management for distributed workforces. The combined capability is expected to appeal to companies looking to standardize how employees spend company funds and access benefits across regions, while maintaining governance and compliance controls. Remote is backed by investors including SoftBank, Accel, Sequoia, Index Ventures, Two Sigma Ventures, General Catalyst, and B Capital. Atlas has been backed by a group of investors, including Hi Ventures, Daniel Gross, Jason Calacanis, Claire Hughes Johnson, Lauran Behrens, Oskar Hjertonsson, 2048 Ventures, Ride Ventures, First Row Partners, Michael Manne, and Ben Tossel. Financial terms of the acquisition were not disclosed. KEY QUOTES: “The complexity of cross-border financial management is one of the last great barriers to truly efficient global operations. From the first time I met the Atlas team, I was"],"highlightScores":[-0.027099609375],"image":"https://cdn.pulse2.com/cdn/2026/01/Remote-Logo.jpeg","favicon":"https://pulse2.com/wp-content/themes/pulse2/images/icons/apple-touch-icon.png"},{"id":"https://hrtechfeed.com/remote-acquires-expense-management-platform/","title":"Remote Acquires Expense Management Platform - HR Tech Feed","url":"https://hrtechfeed.com/remote-acquires-expense-management-platform/","publishedDate":"2026-01-20T00:00:00.000Z","author":"HR Tech Guy","text":"Remote Acquires Expense Management Platform - HR Tech Feed \n\nx\n\n \n\n \n\nRead Time2 Minute, 57 Second\n\nAcquisition will bolster Remote’s HR and payroll platform with integrated financial tools to streamline operations for modern workforces\n\nSAN FRANCISCO — Remote, the leading global employment operating system, has completed the acquisition of Atlas, the expense management solution for global teams. The acquisition provides the foundation for a new category of products from Remote to enable customers to offer more holistic and modern employee experiences to their teams.\n\nWith companies of all sizes now hiring far beyond their HQ cities, managing the day-to-day financial operations of a distributed team remains a fragmented process. Led by co-founders Karen Serfaty and Gianina Rossi, Atlas solves this by offering a unified, AI-native platform for global teams including:\n\n- The Atlas Card: The first global employee card designed specifically for remote teams, allowing companies to manage expenses and stipends for employees worldwide with customized rules and global support.\n- Flexible Points System: Allowing companies to allocate budgets without processing reimbursements, while letting employees select their own perks, such as wellness, transit, or entertainment.\n- Integrated Global Healthcare: The ability to offer and manage local health insurance across multiple key markets, including the U.S., Mexico, Colombia, and Argentina, from a single dashboard.\n\n“The complexity of cross-border financial management is one of the last great barriers to truly efficient global operations,” said Job van der Voort, co-founder and CEO of Remote. “From the first time I met the Atlas team, I was impressed by the elegance and depth of the solutions they’ve built to this problem. By building Atlas into Remote, we can more effectively solve those daily headaches for our customers and make life better for their teams. I’m thrilled to welcome such a talented group of builders who share our obsession with making global employment feel truly local.”\n\n See also Remote Expands Platform With an HRIS\n\n“We started Atlas because we believe that everyone, regardless of where they are located, should have access to the best working conditions. Part of solving this problem means providing global employees with access to financial solutions like a personal employee card and benefits such as healthcare,” said Karen Serfaty, co-founder and CEO of Atlas. “We are big fans of the work that Job, Marcelo, and the Remote team have done to advance the vision of a global workforce. We are joining Remote because we believe that we can get further together. We are very excited for the future of global employment and for all things to come for teams choosing Remote in 2026.”\n\nAbout Remote: Talent is everywhere, opportunity should be too. Remote’s mission is to create opportunity everywhere by making it simple for companies to find, hire, manage, and pay teams anywhere.","highlights":["Remote Acquires Expense Management Platform - HR Tech Feed \n\nx\n\n \n\n \n\nRead Time2 Minute, 57 Second Acquisition will bolster Remote’s HR and payroll platform with integrated financial tools to streamline operations for modern workforces SAN FRANCISCO — Remote, the leading global employment operating system, has completed the acquisition of Atlas, the expense management solution for global teams. The acquisition provides the foundation for a new category of products from Remote to enable customers to offer more holistic and modern employee experiences to their teams. With companies of all sizes now hiring far beyond their HQ cities, managing the day-to-day financial operations of a distributed team remains a fragmented process. Led by co-founders Karen Serfaty and Gianina Rossi, Atlas solves this by offering a unified, AI-native platform for global teams including: - The Atlas Card: The first global employee card designed specifically for remote teams, allowing companies to manage   ...    employees select their own perks, such as wellness, transit, or entertainment.   ...    including the U.S., Mexico, Colombia, and Argentina, from a single dashboard. “The complexity of cross-border financial management is one of the last great barriers to truly efficient global operations,” said Job van der Voort, co-founder and CEO of Remote. “From the first time I met the Atlas team, I was impressed by the elegance and depth of the solutions they’ve built to this problem. By building Atlas into Remote, we can more effectively solve those daily headaches for our customers and make life better for their teams. I’m thrilled to welcome such a talented group of builders who share our obsession with making global employment feel truly local.” See also Remote Expands Platform With an HRIS “We started Atlas because we believe that everyone, regardless of where they are located, should have access to the best working conditions. Part of solving this problem means providing global employees with access to financial solutions like a personal employee card and benefits such as healthcare,” said Karen Serfaty, co-founder and CEO of Atlas. “We are big fans of the work that Job, Marcelo, and the Remote team have done to advance the vision of a global workforce. We are joining Remote because we believe that we can get further together. We are very excited for the future of global employment and for all things to come for teams choosing Remote in 2026.” About Remote: Talent is everywhere, opportunity should be too. Remote’s mission is to create opportunity everywhere by making it simple for companies to find, hire, manage, and"],"highlightScores":[-0.0947265625],"image":"https://hrtechfeed.com/wp-content/uploads/2020/01/HRTECH-ACQUISITION.png","favicon":"https://hrtechfeed.com/wp-content/uploads/2020/12/cropped-HRTFsocial-1-32x32.png"},{"id":"https://www.onrec.com/news/partnerships/deel-acquires-assemble-to-transform-global-compensation-management","title":"Deel Acquires Assemble to Transform Global Compensation Management","url":"https://www.onrec.com/news/partnerships/deel-acquires-assemble-to-transform-global-compensation-management","author":"Stuart Gentle   Publisher at Onrec","text":"Deel Acquires Assemble to Transform Global Compensation Management | Onrec\n\n# Deel Acquires Assemble to Transform Global Compensation Management\n\nSince our founding in 2019, we’ve empowered businesses to hire, pay, and manage teams in over 150 countries—compliantly and with ease. Today, we’re taking another major step toward streamlining all payroll and HR needs on one platform by acquiring Assemble, a leader in compensation management.\n\n### Why We’re Acquiring Assemble\n\nCompensation management for global teams is no small feat. Companies face the challenge of balancing diverse market rates, compliance complexities, and growing expectations for fairness and transparency. Compensation is more than just numbers on a paycheck; it’s a critical tool for attracting and retaining top talent.\n\nAssemble has earned its reputation as a leader in global compensation management by removing the complexity, friction, and pain out of compensation to help companies make better decisions faster. Here’s what makes their approach stand out:\n\n- Customer-Centric 360 Experience: Assemble’s platform offers tailored dashboards for C-suite executives, HR leaders, team managers, employees, and prospective candidates. These dashboards provide a clear overview of compensation, delivering key insights into pay equity and market benchmarks. By promoting transparency, the platform fosters trust, enhances satisfaction, and ensures everyone feels valued and well-informed.\n- Integration & Insights: The platform integrates effortlessly with leading HRIS solutions, Applicant Tracking Systems (ATS) and cap table tools like Carta to bring your insights together. It also pulls from aggregated and anonymized market data, providing industry insights to ensure a company’s comp strategy is in line with its peers.\n- Easy self-serve platform: Assemble enables companies to create structured compensation plans, manage pay and equity bands, ensure pay transparency, and derive data-driven insights to retain talent in one self-serve platform.\n\nAssemble doesn’t just simplify compensation—it makes it fair, equitable, consistent, competitive and easily explainable. All at scale for global teams.\n\n### What This Means for Our Customers\n\nBy rebuilding Assemble in the Deel platform, we’ll combine Deel’s performance management, payroll and AI tech to create an all-in-one solution for global workforce management. We will enable teams to enforce world-class compensation strategies from start to finish within Deel, connected to everything they need to manage a global workforce. Here’s what you can expect:\n\n- AI-Powered Insights: Use Deel AI to forecast pay trends, recommend adjustments, and optimize pay structures, making smarter decisions faster.\n- Data-Driven Compensation: Assemble creates insights pulled from anonymized market data. Paired with Deel’s dataset of 500,000 workers, your company will gain unparalleled visibility into global pay trends to stay competitive and compliant.\n- One seamless flow fo","highlights":["Deel Acquires Assemble to Transform Global Compensation Management | Onrec # Deel Acquires Assemble to Transform Global Compensation Management Since our founding in 2019, we’ve empowered businesses to hire, pay, and manage teams in over 150 countries—compliantly and with ease. Today, we’re taking another major step toward streamlining all payroll and HR needs on one platform by acquiring Assemble, a leader in compensation management. ### Why We’re Acquiring Assemble Compensation management for global teams is no small feat. Companies face the challenge of balancing diverse market rates, compliance complexities, and growing expectations for fairness and transparency. Compensation is more than just numbers on a paycheck; it’s a critical tool for attracting and retaining top talent. Assemble has earned its reputation as a leader in global compensation management by removing the complexity, friction, and pain out of compensation to help companies make better decisions faster. Here’s what makes their approach stand   ...    - Customer-Centric 360 Experience: Assemble’s platform offers tailored dashboards for C-suite executives, HR leaders,   ...    (ATS) and cap table tools like Carta to bring your insights together. It also pulls from aggregated and anonymized market data, providing industry insights to ensure a company’s comp strategy is in line with its peers.   ...    bands, ensure pay transparency, and derive data-driven insights to retain talent in one self-serve platform. Assemble doesn’t just simplify compensation—it makes it fair, equitable, consistent, competitive and easily explainable. All at scale for global teams. ### What This Means for Our Customers By rebuilding Assemble in the Deel platform, we’ll combine Deel’s performance management, payroll and AI tech to create an all-in-one solution for global workforce management. We will enable teams to enforce world-class compensation strategies from start to finish within Deel, connected to everything they need to manage a global workforce. Here’s what you can expect: - AI-Powered Insights: Use Deel AI to forecast pay trends, recommend adjustments, and optimize pay structures, making smarter decisions faster. - Data-Driven Compensation: Assemble creates insights pulled from anonymized market data. Paired with Deel’s dataset of 500,000 workers, your company will gain unparalleled visibility into global pay trends to stay competitive and   ...    - One seamless flow for"],"highlightScores":[-0.0179443359375],"favicon":"https://www.onrec.com/sites/onrec/directory/files/favicon.jpg"},{"id":"https://www.reuters.com/technology/deel-eyes-more-acquisitions-after-hitting-1-billion-annual-revenue-run-rate-2025-06-03/","title":"Deel eyes more acquisitions after hitting $1 billion annual revenue ...","url":"https://www.reuters.com/technology/deel-eyes-more-acquisitions-after-hitting-1-billion-annual-revenue-run-rate-2025-06-03/","publishedDate":"2025-06-03T00:00:00.000Z","author":"Jaspreet Singh","text":"Deel eyes more acquisitions after hitting $1 billion annual revenue run rate | Reuters\n\nSkip to main content\n\nExclusive news, data and analytics for financial market professionalsLearn more aboutRefinitiv\n\nJune 3 (Reuters) - Payroll startup Deel said on Tuesday it crossed $1 billion annual revenue run rate in the first quarter and has earmarked up to $500 million for acquisitions this year to bolster growth.\n\nCustomers use Deel's global payroll platform to manage their international workforce.\n\nSign up here.\n\nDeel, which acquired Safeguard Global's payroll division for an undisclosed amount in March, allocated an M&A budget of between $200 million and $500 million this year, CEO Alex Bouaziz told Reuters.\n\nThe San Francisco, California-based company is still aiming for a 2026 U.S. initial public offering, but it depends on macroeconomic conditions.\n\nDeel said its revenue rose 75% for the twelve months ended April 30. It reported earnings before interest, taxes, depreciation, and amortization margin of 16% for the first quarter, ended March 31.\n\nBouaziz said he does not know if the company will be able to keep growing at the same level, but \"we are going to try our best.\"\n\nFounded in 2019, Deel provides services to help companies hire international employees and contractors while ensuring compliance with local labor laws. It also automates payroll processing for businesses operating across multiple countries.\n\nDeel — which has 6,500 employees and more than 35,000 customers including AI startup ElevenLabs, Nike (NKE.N), opens new tab, Klarna (KLAR.N), opens new tab, and Shopify (SHOP.TO), opens new tab— competes with companies such as Rippling, Omnipresent and Automatic Data Processing (ADP.O), opens new tab.\n\n\"We believe in the idea that typically, the service you get is tied to how much you are willing to pay ... Deel is a bit more premium than most companies,\" Bouaziz said.\n\nIn March, rival Rippling filed a lawsuit against Deel alleging racketeering, misappropriation of trade secrets and unfair competition, among others.\n\nDeel filed its own lawsuit for defamation in April, saying Rippling has been running a multi-year smear campaign against it. The company also believes the allegations by Rippling are driven by the fact that \"Deel is winning in the market.\"\n\nReporting by Jaspreet Singh in Bengaluru; Editing by Alan Barona\n\nOur Standards: The Thomson Reuters Trust Principles., opens new tab\n\nPurchase Licensing Rights\n\n## Technology\n\n### Exclusive: Australia says it may go after app stores, search engines in AI age crackdown\n\nBusinesscategory· March 1, 2026 · 9:07 PM UTC · ago\n\nAustralia's internet regulator said it may push search engines and app stores to block artificial intelligence services that fail to verify user ages after a Reuters review found more than half had not made public any steps to comply by a deadline ","highlights":["Deel eyes more acquisitions after hitting $1 billion annual revenue run rate | Reuters\n\nSkip to main content   ...    June 3 (Reuters) - Payroll startup Deel said on Tuesday it crossed $1 billion annual revenue run rate in the first quarter and has earmarked up to $500 million for acquisitions this year to bolster growth. Customers use Deel's global payroll platform to manage their international workforce.\n\nSign up here. Deel, which acquired Safeguard Global's payroll division for an undisclosed amount in March, allocated an M&A budget of between $200 million and $500 million this year, CEO Alex Bouaziz told Reuters. The San Francisco, California-based company is still aiming for a 2026 U.S. initial public offering, but it depends on macroeconomic conditions. Deel said its revenue rose 75% for the twelve months ended April 30. It reported earnings before interest, taxes,   ...    Bouaziz said he does not know if the company will be able to keep growing at the same level, but \"we are going to try   ...    Founded in 2019, Deel provides services to help companies hire international employees and contractors while ensuring   ...    Deel — which has 6,500 employees and more than 35,000 customers including AI startup ElevenLabs, Nike (NKE.N), opens new tab, Klarna (KLAR.N), opens new tab, and Shopify (SHOP.TO), opens new tab— competes with companies such as Rippling, Omnipresent and Automatic Data Processing (ADP.O), opens new tab. \"We believe in the idea that typically, the service you get is tied to how much you are willing to pay ... Deel is a bit more premium than most companies,\" Bouaziz said. In March, rival Rippling filed a lawsuit against Deel alleging racketeering, misappropriation of trade secrets and unfair competition, among others. Deel filed its own lawsuit for defamation in April, saying Rippling has been running a multi-year smear campaign against it. The company also believes the allegations by Rippling are driven by the fact that \"Deel is winning in the   ...    Reporting by Jaspreet Singh in Bengaluru; Editing by Alan Barona   ...    ### Exclusive: Australia says it may go after app stores, search engines in AI age crackdown Businesscategory· March 1, 2026 · 9:07 PM UTC · ago Australia's internet regulator said it may push"],"highlightScores":[0.10791015625],"image":"https://www.reuters.com/resizer/v2/466BJJQ7PVGY5O53NZ3KL65MHM.png?auth=b9c3bf166c40a6778eb5672993fde7c30a15f48329026674eff92afd8da1d0ca&height=1005&width=1920&quality=80&smart=true","favicon":"https://www.reuters.com/pf/resources/images/reuters/favicon/tr_fvcn_kinesis_32x32_v2.ico?d=353"}],"searchTime":1103.6,"costDollars":{"total":0.007,"search":{"neural":0.007}}}